{
  "intro": "Bonjour!",
  "image": {
    "src": "../../images/hi.png",
    "alt": "Waving Hand Drawing"
  },
  "title": "I'm Chloé BENZ",
  "subtitle": {
    "prefix": "I'm an ",
    "highlight": "Aerospace Engineer",
    "suffix": "."
  },
  "description": "But also a dancer, a photographer, and many other things... I never settle. I constantly challenge myself, in every aspect of my life. Every day is an opportunity for learning!",
  "socialProfiles": {
    "from": ["LinkedIn", "Github", "Mail"],
    "showIcons": true
  }
}
